embedops_cli/__init__.py
embedops_cli/ci_config_loader.py
embedops_cli/config.py
embedops_cli/docker_run.py
embedops_cli/embedops_authorization.py
embedops_cli/embedops_cli.py
embedops_cli/embedops_cli_internal.py
embedops_cli/embedops_cli_plugins.py
embedops_cli/environment_utilities.py
embedops_cli/eo_types.py
embedops_cli/settings.toml
embedops_cli/telemetry.py
embedops_cli/utilities.py
embedops_cli/version.py
embedops_cli/api/__init__.py
embedops_cli/api/api_client.py
embedops_cli/api/configuration.py
embedops_cli/api/default_api.py
embedops_cli/api/rest.py
embedops_cli/api/api/__init__.py
embedops_cli/api/api/default_api.py
embedops_cli/api/models/__init__.py
embedops_cli/api/models/any_of_metric_create_props_value.py
embedops_cli/api/models/aws_access_key.py
embedops_cli/api/models/aws_access_key_access_key.py
embedops_cli/api/models/branch_names.py
embedops_cli/api/models/ci_o_auth_token_update_props.py
embedops_cli/api/models/ci_o_auth_tokens.py
embedops_cli/api/models/ci_provider.py
embedops_cli/api/models/ci_run.py
embedops_cli/api/models/ci_run_artifact.py
embedops_cli/api/models/ci_run_artifact_create_props.py
embedops_cli/api/models/ci_run_create_props.py
embedops_cli/api/models/ci_run_id_artifacts_body.py
embedops_cli/api/models/ci_run_type.py
embedops_cli/api/models/ci_run_update_props.py
embedops_cli/api/models/created_at.py
embedops_cli/api/models/fleet_device.py
embedops_cli/api/models/gitlab_access_token.py
embedops_cli/api/models/gitlab_access_token_token.py
embedops_cli/api/models/group.py
embedops_cli/api/models/group_create_props.py
embedops_cli/api/models/group_update_props.py
embedops_cli/api/models/hil_run_create_props.py
embedops_cli/api/models/inline_response2001.py
embedops_cli/api/models/inline_response2002.py
embedops_cli/api/models/inline_response400.py
embedops_cli/api/models/inline_response404.py
embedops_cli/api/models/job_def.py
embedops_cli/api/models/job_def_create_props.py
embedops_cli/api/models/job_def_update_props.py
embedops_cli-0.3.52.dist-info/LICENSE
embedops_cli-0.3.52.dist-info/METADATA
embedops_cli-0.3.52.dist-info/WHEEL
embedops_cli-0.3.52.dist-info/entry_points.txt
embedops_cli-0.3.52.dist-info/top_level.txt
embedops_cli-0.3.52.dist-info/RECORD
