Metadata-Version: 2.2
Name: embedops-cli
Version: 0.3.52
Summary: EmbedOps Command Line Tools
Home-page: https://embedops.io
Author: Dojo Five, LLC
Author-email: embedops@dojofive.com
Classifier: Development Status :: 3 - Alpha
Classifier: Intended Audience :: Developers
Classifier: Environment :: Console
Classifier: Topic :: Software Development :: Build Tools
Classifier: Topic :: Software Development :: Embedded Systems
Classifier: License :: Free To Use But Restricted
Classifier: Programming Language :: Python :: 3
License-File: LICENSE
Requires-Dist: dynaconf==3.1.7
Requires-Dist: setuptools>=21.0.0
Requires-Dist: python-dotenv>=0.19.0
Requires-Dist: termcolor>=2.3.0
Requires-Dist: click==7.1.2
Requires-Dist: colorama==0.4.6
Requires-Dist: InquirerPy==0.3.4
Requires-Dist: pyyaml==6.0.1
Requires-Dist: boto3==1.26.165
Requires-Dist: sseclient-py==1.7.2
Requires-Dist: pyfatfs>=1.0.5
Requires-Dist: pywinpty==2.0.12; sys_platform == "win32"
Requires-Dist: requests==2.26.0
Requires-Dist: certifi>=2023.11.17
Requires-Dist: six>=1.10
Requires-Dist: python_dateutil>=2.5.3
Requires-Dist: urllib3<2.0.0,>=1.15.1
Requires-Dist: bs4>=0.0.1
Requires-Dist: lxml
